connector_glb/__init__.py
connector_glb/connector.py
connector_glb/formatter.py
connector_glb-0.0.9.dist-info/METADATA
connector_glb-0.0.9.dist-info/WHEEL
connector_glb-0.0.9.dist-info/licenses/LICENSE
connector_glb-0.0.9.dist-info/RECORD
