Metadata-Version: 2.3
Name: connector_glb
Version: 0.0.9
Summary: Pacote para facilitar a conexão com o banco de dados
Author-email: Igor Jasenovski <igormjsk@gmail.com>
Classifier: License :: OSI Approved :: MIT License
Classifier: Operating System :: OS Independent
Classifier: Programming Language :: Python :: 3
Requires-Python: >=3.8
